<?xml version="1.0" encoding="utf-8"?>
<Template>
  <BranchType type="byte" default="1" description="What kind of branch to use.">
	<Enum description="TREE_A01" value="0" />
    <Enum description="TREE_A02" value="1" />
    <Enum description="TREE_A03" value="2" />
    <Enum description="TREE_B01" value="3" />
    <Enum description="TREE_B02" value="4" />
    <Enum description="TREE_B03" value="5" />
  </BranchType>
  
  <Scale type="float" default="1" description="This object's scaling." />
  <TimeType type="byte" description="TODO">
    <Enum description="Local" value="0" />
    <Enum description="Global" value="1" />
  </TimeType>
  
  <WindHorzAngle type="float" default="90" description="The angle of the wind that blows against this tree's leaves while the wind is blowing horizontally." />
  <WindHorzAngleWidth type="float" default="50" description="TODO" />
  <WindHorzAngleCycle type="float" default="2" description="How long the wind blows horizontally, before blowing vertically instead." />
  <WindVertAngle type="float" default="10" description="The angle of the wind that blows against this tree's leaves while the wind is blowing vertically." />
  <WindVertAngleWidth type="float" default="10" description="TODO" />
  <WindVertAngleCycle type="float" default="1" description="How long the wind blows vertically, before blowing horizontally instead." />
  
  <WindSpeedMin type="float" default="100" description="The minimum speed of the wind which blows against this tree's leaves." />
  <WindSpeedMax type="float" default="1400" description="The maximum speed of the wind which blows against this tree's leaves." />
  <WindSpeedCycle type="float" default="3" description="How long the wind blows at one speed before picking another random speed in-between WindSpeedMin and WindSpeedMax." />
  
  <Extra type="model" value="w5_obj_palmtreeA01.model" condition="BranchType == 0" />
  <Extra type="model" value="w5_obj_palmtreeA02.model" condition="BranchType == 1" />
  <Extra type="model" value="w5_obj_palmtreeA03.model" condition="BranchType == 2" />
  <Extra type="model" value="w5_obj_palmtreeB01.model" condition="BranchType == 3" />
  <Extra type="model" value="w5_obj_palmtreeB02.model" condition="BranchType == 4" />
  <Extra type="model" value="w5_obj_palmtreeB03.model" condition="BranchType == 5" />
  
  <Extra type="description" value="literally just palm trees" />
  <Extra type="RawByteLength" length="48" />
</Template>