<?xml version="1.0" encoding="utf-8"?>
<Template>
  <SearchDistance type="float" default="400" description="How far this object can see when searching for a player to attack." />
  <MoveSpeed type="float" default="10" description="How fast this object can move." />
  <MaxMoveDistance type="float" default="-1" description="How far this object can move. Set to -1 for no limit." />
  <IsEventOn type="bool" description="Whether this object is must be triggered by something first, or is active/visible by default." />
  <JumpAttack type="bool" default="false" description="Whether this enemy can attack the player via jumping?" />
  <In3D type="bool" default="true" description="Whether this object is in a 3D section, or a 2D section." />
  <IsFallStart type="bool" default="false" description="Whether this object spawns in its falling state." />
  
  <IsTreadGrass type="bool" description="Whether this object is walking through grass?" />
  <UpdateMaterial type="bool" description="Whether this object's material needs to be updated each frame?" />
  
  <Extra type="model" value="enm_motora02.model" />
  <Extra type="description" value="These are just MotoBugs....." />
  <Extra type="RawByteLength" length="20" />
</Template>